jetson_tello/__init__.py
jetson_tello/app.py
jetson_tello/video.py
jetson_tello-1.1.8.dist-info/LICENSE
jetson_tello-1.1.8.dist-info/METADATA
jetson_tello-1.1.8.dist-info/WHEEL
jetson_tello-1.1.8.dist-info/top_level.txt
jetson_tello-1.1.8.dist-info/RECORD
