Metadata-Version: 2.1
Name: jetson-tello
Version: 1.1.8
Summary: Tello drone integration with Jetson
Home-page: https://github.com/robagar/jetson-tello
Author: Rob Agar
Author-email: tello_asyncio@fastmail.net
License: LGPL
Project-URL: Documentation, https://jetson-tello.readthedocs.io/en/latest/
Platform: UNKNOWN
Requires-Python: >=3.6
License-File: LICENSE
Requires-Dist: tello-asyncio (>=1.6.0)
Requires-Dist: numpy (>=1.20.3)
